web_crawler_for_map_services_shared/__init__.py
web_crawler_for_map_services_shared/db_access/__init__.py
web_crawler_for_map_services_shared/db_access/db_context.py
web_crawler_for_map_services_shared/db_access/daos/__init__.py
web_crawler_for_map_services_shared/db_access/daos/health_check_dao.py
web_crawler_for_map_services_shared/db_access/daos/proxy_config_dao.py
web_crawler_for_map_services_shared/db_access/daos/service_auth_keys_dao.py
web_crawler_for_map_services_shared/db_access/daos/task_queue_dao.py
web_crawler_for_map_services_shared/db_access/dtos/__init__.py
web_crawler_for_map_services_shared/db_access/dtos/proxy_config_dto.py
web_crawler_for_map_services_shared/db_access/dtos/service_authentication_key_dto.py
web_crawler_for_map_services_shared/db_access/dtos/task_queue_dto.py
web_crawler_for_map_services_shared/db_access/utils/__init__.py
web_crawler_for_map_services_shared/db_access/utils/retry_decorator.py
web_crawler_for_map_services_shared/enums/__init__.py
web_crawler_for_map_services_shared/enums/crawl_status.py
web_crawler_for_map_services_shared/models/__init__.py
web_crawler_for_map_services_shared/models/legal_information_model.py
web_crawler_for_map_services_shared/models/outlet_model.py
web_crawler_for_map_services_shared/models/outlet_scraping_request.py
web_crawler_for_map_services_shared/models/outlet_scraping_result.py
web_crawler_for_map_services_shared-0.1.5.dist-info/METADATA
web_crawler_for_map_services_shared-0.1.5.dist-info/WHEEL
web_crawler_for_map_services_shared-0.1.5.dist-info/top_level.txt
web_crawler_for_map_services_shared-0.1.5.dist-info/RECORD
